qvf.so
quiver_feature/__init__.py
quiver_feature/common.py
quiver_feature/dist_helper.py
quiver_feature/dist_tensor_pgas.py
quiver_feature/dist_tensor_rpc.py
quiver_feature/local_tensor_pgas.py
quiver_feature/tensor_loader.py
quiver_feature/utils.py
quiver_feature/multiprocessing/__init__.py
quiver_feature/multiprocessing/reductions.py
quiver_feature-0.1.3.dist-info/LICENSE
quiver_feature-0.1.3.dist-info/METADATA
quiver_feature-0.1.3.dist-info/WHEEL
quiver_feature-0.1.3.dist-info/top_level.txt
quiver_feature-0.1.3.dist-info/RECORD
